mdkit/__init__.py
mdkit/main.py
mdkit/utils.py
mdkit_pcl-0.1.3.dist-info/METADATA
mdkit_pcl-0.1.3.dist-info/WHEEL
mdkit_pcl-0.1.3.dist-info/entry_points.txt
mdkit_pcl-0.1.3.dist-info/top_level.txt
mdkit_pcl-0.1.3.dist-info/RECORD
