Metadata-Version: 2.4
Name: mdkit-pcl
Version: 0.1.3
Summary: A molecular dynamics simulation toolkit
Home-page: https://github.com/yourusername/mdkit
Author: Pengcheng Li
Author-email: your.email@example.com
Classifier: Programming Language :: Python :: 3
Classifier: License :: OSI Approved :: MIT License
Classifier: Operating System :: OS Independent
Requires-Python: >=3.6
Requires-Dist: rich
Requires-Dist: numpy
Requires-Dist: periodictable
Dynamic: author
Dynamic: author-email
Dynamic: classifier
Dynamic: description
Dynamic: description-content-type
Dynamic: home-page
Dynamic: requires-dist
Dynamic: requires-python
Dynamic: summary
